bogmark/bases/__init__.py
bogmark/bases/requester.py
bogmark/logger/__init__.py
bogmark/logger/configs.py
bogmark/logger/formatters.py
bogmark/logger/mlogger.py
bogmark/logger/styles.py
bogmark/logger/tools.py
bogmark/rabbitmq/__init__.py
bogmark/rabbitmq/connection.py
bogmark/rabbitmq/message.py
bogmark/rabbitmq/worker.py
bogmark/server/__init__.py
bogmark/server/assebmly.py
bogmark/server/configs.py
bogmark/server/dependecies.py
bogmark/server/errors.py
bogmark/server/middlewares/__init__.py
bogmark/server/middlewares/headers.py
bogmark/server/middlewares/logs.py
bogmark/server/middlewares/msgpack.py
bogmark/server/middlewares/prometheus.py
bogmark/server/mixin.py
bogmark/server/responses.py
bogmark/shared/tools.py
bogmark/structures/__init__.py
bogmark/structures/context.py
bogmark/structures/response.py
bogmark-0.1.4.post7.dist-info/WHEEL
bogmark-0.1.4.post7.dist-info/METADATA
bogmark-0.1.4.post7.dist-info/RECORD
